econ_legalizer/__init__.py
econ_legalizer/main.py
econ_legalizer/prompts.py
econ_legalizer-2025.12.21195956.dist-info/METADATA
econ_legalizer-2025.12.21195956.dist-info/WHEEL
econ_legalizer-2025.12.21195956.dist-info/top_level.txt
econ_legalizer-2025.12.21195956.dist-info/RECORD
