Metadata-Version: 2.4
Name: econ-legalizer
Version: 2025.12.21195956
Summary: econ-legalizer is a package that extracts structured summaries and insights from text input on regional economic and legal issues.
Author-email: econ-legalizer <hi@eugene.plus>
License: MIT
Project-URL: Homepage, https://github.com/chigwell/econ-legalizer
Requires-Python: >=3.9
Requires-Dist: langchain-llm7>=0.0.0
Requires-Dist: llmatch-messages>=0.0.0
Requires-Dist: langchain-core>=0.3.0
